example/__init__.py
example/hello_world.py
jcdiq/__init__.py
jcdiq/hello_world.py
jcdiq-0.1.dist-info/LICENSE
jcdiq-0.1.dist-info/METADATA
jcdiq-0.1.dist-info/WHEEL
jcdiq-0.1.dist-info/top_level.txt
jcdiq-0.1.dist-info/RECORD
